faceext.py
faceext-0.0.3.dist-info/METADATA
faceext-0.0.3.dist-info/WHEEL
faceext-0.0.3.dist-info/entry_points.txt
faceext-0.0.3.dist-info/top_level.txt
faceext-0.0.3.dist-info/RECORD
