Metadata-Version: 2.1
Name: faceext
Version: 0.0.3
Summary: faceext for hiding all of your clothes and background except your face
Home-page: https://github.com/y-takefuji/faceext
Author: yoshiyasu takefuji
Author-email: takefuji@keio.jp
License: UNKNOWN
Project-URL: Bug Tracker, https://github.com/y-takefuji/faceext
Platform: UNKNOWN
Classifier: Programming Language :: Python :: 3
Classifier: License :: OSI Approved :: MIT License
Classifier: Operating System :: OS Independent
Requires-Python: >=3.8
